writeback.v
module writeback (
    // Input signals from memory stage
    input wire [63:0] ReadData,       // Data read from memory
    input wire [63:0] ALUResult,      // Result from ALU
    input wire [4:0] Rd,              // Destination register
    
    // Control signals from memory stage
    input wire MemtoReg,              // Memory to register control
    input wire RegWrite,              // Register write control
    
    // Output signals to register file
    output wire [63:0] WriteData,     // Data to write to register file
    output wire [4:0] WriteReg,       // Register to write to
    output wire RegWriteOut           // Register write control
);
    // Select data to write back to register file
    assign WriteData = MemtoReg ? ReadData : ALUResult;
    
    // Pass through destination register
    assign WriteReg = Rd;
    
    // Pass through register write control
    assign RegWriteOut = RegWrite;
    
endmodule

rtl/memory.v
module memory (
    input wire clk,
    input wire reset,
    input wire [63:0] ALUResult,
    input wire [63:0] WriteData,
    input wire [4:0] Rd,
    input wire Zero,
    input wire BranchTaken,
    input wire MemRead,
    input wire MemWrite,
    input wire MemtoReg,
    input wire RegWrite,
    output wire [63:0] ReadData,
    output wire [63:0] ALUResultOut,
    output wire [4:0] RdOut,
    output wire BranchTakenOut,
    output wire MemtoRegOut,
    output wire RegWriteOut
);

// Data memory: 1024 x 64-bit = 8KB
reg [63:0] mem [0:1023]/*verilator public*/;
reg [63:0] read_data;

// Memory address calculation (byte to word)
wire [9:0] mem_addr = ALUResult[12:3];

// Check if address is valid (< 8192 bytes = 1024 words * 8 bytes)
wire addr_valid = (ALUResult < 64'd8192);  

// Memory read (combinational)
always @(*) begin
    if (MemRead && addr_valid)
        read_data = mem[mem_addr];
    else
        read_data = 64'd0;
end

// Memory write (synchronous)
always @(posedge clk) begin
    if (!reset && MemWrite && addr_valid) begin
        mem[mem_addr] <= WriteData;
    end
end

assign ReadData = read_data;
assign ALUResultOut = ALUResult;
assign RdOut = Rd;
assign BranchTakenOut = BranchTaken;
assign MemtoRegOut = MemtoReg;
assign RegWriteOut = RegWrite;

endmodule

rtl/execute.v
module execute (
    input wire [63:0] ReadData1,
    input wire [63:0] ReadData2,
    input wire [63:0] ImmExt,
    input wire [4:0] Rd,
    input wire [3:0] ALUOp,
    input wire ALUSrc,
    input wire Branch,
    input wire MemRead,
    input wire MemtoReg,
    input wire MemWrite,
    input wire RegWrite,
    
    output wire [63:0] ALUResult,
    output wire Zero,
    output wire BranchTaken,
    output wire [63:0] WriteData,
    output wire [4:0] RdOut,
    output wire MemReadOut,
    output wire MemtoRegOut,
    output wire MemWriteOut,
    output wire RegWriteOut
);

    // ALU input selection
    wire [63:0] ALUInput2 = ALUSrc ? ImmExt : ReadData2;
    
    // ALU computation
    reg [63:0] alu_result;
    reg zero_flag;
    
    always @(*) begin
        case (ALUOp)
            4'b0010: alu_result = ReadData1 + ALUInput2;  // ADD
            4'b0110: alu_result = ReadData1 - ALUInput2;  // SUB
            4'b0111: alu_result = ReadData1 & ALUInput2;  // AND
            4'b0001: alu_result = ReadData1 | ALUInput2;  // OR
            4'b0000: alu_result = ReadData1 + ALUInput2;  // ADD (for ld/sd)
            default: alu_result = 64'd0;
        endcase
        
        zero_flag = (alu_result == 64'd0);
    end
    
    // Branch decision
    assign BranchTaken = Branch & zero_flag;
    
    // Outputs
    assign ALUResult = alu_result;
    assign Zero = zero_flag;
    assign WriteData = ReadData2;
    assign RdOut = Rd;
    
    // Control forwarding
    assign MemReadOut = MemRead;
    assign MemtoRegOut = MemtoReg;
    assign MemWriteOut = MemWrite;
    assign RegWriteOut = RegWrite;

endmodule

rtl/decode.v
module decode (
    input wire clk,
    input wire reset,
    input wire [31:0] Instr,
    input wire ExtRegWrite,
    output wire RegWrite,
    input wire [4:0] WriteReg,
    input wire [63:0] WriteData,
    output wire [63:0] ReadData1,
    output wire [63:0] ReadData2,
    output wire [63:0] ImmExt,
    output wire [4:0] Rd,
    output wire Branch,
    output wire MemRead,
    output wire MemtoReg,
    output wire [3:0] ALUOp,
    output wire MemWrite,
    output wire ALUSrc,
    output wire RegDst
);

    wire [6:0] opcode = Instr[6:0];
    wire [4:0] rd_addr = Instr[11:7];
    wire [2:0] funct3 = Instr[14:12];
    wire [4:0] rs1_addr = Instr[19:15];
    wire [4:0] rs2_addr = Instr[24:20];
    wire [6:0] funct7 = Instr[31:25];
    
    // Register file
    reg [63:0] registers [0:31]/*verilator public*/;
    
    // Register read (combinational with x0 hardwired to 0)
    assign ReadData1 = (rs1_addr == 5'd0) ? 64'd0 : registers[rs1_addr];
    assign ReadData2 = (rs2_addr == 5'd0) ? 64'd0 : registers[rs2_addr];
    
    // Register write (synchronous)
    always @(posedge clk) begin
        if (ExtRegWrite && (WriteReg != 5'd0))
            registers[WriteReg] <= WriteData;
    end
    
    // Immediate generation (combinational)
    reg [63:0] imm;
    always @(*) begin
        case (opcode)
            7'b0000011: // I-type (ld)
                imm = {{52{Instr[31]}}, Instr[31:20]};
            7'b0100011: // S-type (sd)
                imm = {{52{Instr[31]}}, Instr[31:25], Instr[11:7]};
            7'b1100011: // B-type (beq)
                imm = {{51{Instr[31]}}, Instr[31], Instr[7], Instr[30:25], Instr[11:8], 1'b0};
            default:
                imm = 64'd0;
        endcase
    end
    assign ImmExt = imm;
    
    // Control signal generation
    reg branch, memRead, memtoReg, memWrite, aluSrc, regDst, regWriteInt;
    reg [3:0] aluOp;
    
    always @(*) begin
        // Defaults
        {branch, memRead, memtoReg, memWrite, aluSrc, regDst, regWriteInt} = 7'b0;
        aluOp = 4'b0000;
        
        case (opcode)
            7'b0110011: begin // R-type
                regDst = 1'b1;
                regWriteInt = 1'b1;
                case ({funct3, funct7[5]})
                    4'b0000: aluOp = 4'b0010; // add
                    4'b0001: aluOp = 4'b0110; // sub
                    4'b1110: aluOp = 4'b0111; // and
                    4'b1100: aluOp = 4'b0001; // or
                    default: aluOp = 4'b0000;
                endcase
            end
            
            7'b0000011: begin // ld (I-type load)
                regDst = 1'b1;
                aluSrc = 1'b1;
                memtoReg = 1'b1;
                regWriteInt = 1'b1;
                memRead = 1'b1;
            end
            
            7'b0100011: begin // sd (S-type store)
                aluSrc = 1'b1;
                memWrite = 1'b1;
            end
            
            7'b1100011: begin // beq (B-type branch)
                branch = 1'b1;
                aluOp = 4'b0110;
            end
        endcase
    end
    
    assign Branch = branch;
    assign MemRead = memRead;
    assign MemtoReg = memtoReg;
    assign ALUOp = aluOp;
    assign MemWrite = memWrite;
    assign ALUSrc = aluSrc;
    assign RegDst = regDst;
    assign RegWrite = regWriteInt;
    
    // Rd output (0 for S-type and B-type)
    assign Rd = (opcode == 7'b0100011 || opcode == 7'b1100011) ? 5'd0 : rd_addr;

endmodule

fetch.v
module instruction_fetch (
    input wire clk,              // System clock
    input wire rst_n,            // Active low reset
    input wire stall,            // Stall signal from hazard unit
    input wire branch_taken,     // Branch taken signal
    input wire [63:0] branch_target_addr, // Branch target address
    output reg [31:0] instruction,  // 32-bit instruction fetched
    output reg [63:0] pc_current,   // Current program counter
    output reg [63:0] pc_next       // Next program counter (pc+4)
);

    // Instruction memory (could be replaced with actual memory interface)
    reg [31:0] instr_mem [0:1023];  // 1024 entries of 32-bit instructions
    
    // Initialize PC
    initial begin
        pc_current = 64'h0000_0000_0000_0000;  // Starting address
        pc_next = 64'h0000_0000_0000_0004;     // Initialize pc_next as well
        instruction = 32'h0000_0000;           // Initialize instruction to NOP
    end
    
    // Instruction fetch logic
    always @(posedge clk or negedge rst_n) begin
        if (!rst_n) begin
            // Reset state
            pc_current <= 64'h0000_0000_0000_0000;
            pc_next <= 64'h0000_0000_0000_0004;
            instruction <= 32'h0000_0000;  // NOP instruction
        end 
        else if (!stall) begin
            // Update PC
            if (branch_taken) begin
                pc_current <= branch_target_addr;  // Jump to branch target
                pc_next <= branch_target_addr + 64'h4;
            end 
            else begin
                pc_current <= pc_next;  // Normal sequential execution
                pc_next <= pc_next + 64'h4;
            end
            
            // Fetch instruction from memory based on PC
            // The memory is accessed using the PC value directly
            // For proper alignment, we need to select the correct word
            instruction <= instr_mem[(pc_current >> 2)];
        end
        // If stalled, maintain the current state (PC and instruction remain unchanged)
    end
    
    // Memory initialization could be done here or via external file
    // initial $readmemh("program.hex", instr_mem);

endmodule

rtl/single_cycle_processor.v
// Single-Cycle RISC-V Processor Implementation
`timescale 1ns/1ps

module single_cycle_processor (
    input wire clk,
    input wire reset
);

    // Fetch stage outputs
    wire [31:0] instruction /*verilator public*/;
    wire [63:0] pc_current /*verilator public*/;
    
    // Decode stage outputs
    wire [63:0] read_data1, read_data2, imm_ext;
    wire [4:0] rd;
    wire branch, mem_read, mem_to_reg, mem_write, alu_src, reg_write;
    wire [3:0] alu_op;
    
    // Execute stage outputs
    wire [63:0] alu_result, write_data_mem;
    wire zero, branch_taken;
    wire [4:0] rd_ex;
    wire mem_read_ex, mem_to_reg_ex, mem_write_ex, reg_write_ex;
    
    // Memory stage outputs
    wire [63:0] read_data_mem, alu_result_mem;
    wire [4:0] rd_mem;
    wire mem_to_reg_mem, reg_write_mem;
    
    // Writeback stage outputs
    wire [63:0] write_data_reg;
    wire [4:0] write_reg;
    wire reg_write_wb;
    
    // Branch target calculation
    wire [63:0] branch_target_addr = (pc_current - 64'd4) + imm_ext;    
    // Instruction Fetch
    instruction_fetch if_stage (
        .clk(clk),
        .rst_n(~reset),
        .stall(1'b0),
        .branch_taken(branch_taken),
        .branch_target_addr(branch_target_addr),
        .instruction(instruction),
        .pc_current(pc_current)
    );
    
    // Decode
    decode id_stage (
        .clk(clk),
        .reset(reset),
        .Instr(instruction),
        .ExtRegWrite(reg_write_wb),
        .RegWrite(reg_write),
        .WriteReg(write_reg),
        .WriteData(write_data_reg),
        .ReadData1(read_data1),
        .ReadData2(read_data2),
        .ImmExt(imm_ext),
        .Rd(rd),
        .Branch(branch),
        .MemRead(mem_read),
        .MemtoReg(mem_to_reg),
        .ALUOp(alu_op),
        .MemWrite(mem_write),
        .ALUSrc(alu_src),
        .RegDst()  // Unused in single-cycle
    );
    
    // Execute
    execute ex_stage (
        .ReadData1(read_data1),
        .ReadData2(read_data2),
        .ImmExt(imm_ext),
        .Rd(rd),
        .ALUOp(alu_op),
        .ALUSrc(alu_src),
        .Branch(branch),
        .MemRead(mem_read),
        .MemtoReg(mem_to_reg),
        .MemWrite(mem_write),
        .RegWrite(reg_write),
        .ALUResult(alu_result),
        .Zero(zero),
        .BranchTaken(branch_taken),
        .WriteData(write_data_mem),
        .RdOut(rd_ex),
        .MemReadOut(mem_read_ex),
        .MemtoRegOut(mem_to_reg_ex),
        .MemWriteOut(mem_write_ex),
        .RegWriteOut(reg_write_ex)
    );
    
    // Memory
    memory mem_stage (
        .clk(clk),
        .reset(reset),
        .ALUResult(alu_result),
        .WriteData(write_data_mem),
        .Rd(rd_ex),
        .Zero(zero),
        .BranchTaken(branch_taken),
        .MemRead(mem_read_ex),
        .MemWrite(mem_write_ex),
        .MemtoReg(mem_to_reg_ex),
        .RegWrite(reg_write_ex),
        .ReadData(read_data_mem),
        .ALUResultOut(alu_result_mem),
        .RdOut(rd_mem),
        .BranchTakenOut(),  // Unused
        .MemtoRegOut(mem_to_reg_mem),
        .RegWriteOut(reg_write_mem)
    );
    
    // Writeback
    writeback wb_stage (
        .ReadData(read_data_mem),
        .ALUResult(alu_result_mem),
        .Rd(rd_mem),
        .MemtoReg(mem_to_reg_mem),
        .RegWrite(reg_write_mem),
        .WriteData(write_data_reg),
        .WriteReg(write_reg),
        .RegWriteOut(reg_write_wb)
    );

endmodule

waveform.vcd
$version Generated by VerilatedVcd $end
$timescale 1ps $end
 $scope module TOP $end
  $var wire 1 &! clk $end
  $var wire 1 '! reset $end
  $scope module single_cycle_processor $end
   $var wire 1 &! clk $end
   $var wire 1 '! reset $end
   $var wire 32 c instruction [31:0] $end
   $var wire 64 d pc_current [63:0] $end
   $var wire 64 y read_data1 [63:0] $end
   $var wire 64 { read_data2 [63:0] $end
   $var wire 64 f imm_ext [63:0] $end
   $var wire 5 h rd [4:0] $end
   $var wire 1 i branch $end
   $var wire 1 j mem_read $end
   $var wire 1 k mem_to_reg $end
   $var wire 1 l mem_write $end
   $var wire 1 m alu_src $end
   $var wire 1 n reg_write $end
   $var wire 4 o alu_op [3:0] $end
   $var wire 64 } alu_result [63:0] $end
   $var wire 64 { write_data_mem [63:0] $end
   $var wire 1 !! zero $end
   $var wire 1 (! branch_taken $end
   $var wire 5 h rd_ex [4:0] $end
   $var wire 1 j mem_read_ex $end
   $var wire 1 k mem_to_reg_ex $end
   $var wire 1 l mem_write_ex $end
   $var wire 1 n reg_write_ex $end
   $var wire 64 )! read_data_mem [63:0] $end
   $var wire 64 } alu_result_mem [63:0] $end
   $var wire 5 h rd_mem [4:0] $end
   $var wire 1 k mem_to_reg_mem $end
   $var wire 1 n reg_write_mem $end
   $var wire 64 +! write_data_reg [63:0] $end
   $var wire 5 h write_reg [4:0] $end
   $var wire 1 n reg_write_wb $end
   $var wire 64 p branch_target_addr [63:0] $end
   $scope module ex_stage $end
    $var wire 64 y ReadData1 [63:0] $end
    $var wire 64 { ReadData2 [63:0] $end
    $var wire 64 f ImmExt [63:0] $end
    $var wire 5 h Rd [4:0] $end
    $var wire 4 o ALUOp [3:0] $end
    $var wire 1 m ALUSrc $end
    $var wire 1 i Branch $end
    $var wire 1 j MemRead $end
    $var wire 1 k MemtoReg $end
    $var wire 1 l MemWrite $end
    $var wire 1 n RegWrite $end
    $var wire 64 } ALUResult [63:0] $end
    $var wire 1 !! Zero $end
    $var wire 1 (! BranchTaken $end
    $var wire 64 { WriteData [63:0] $end
    $var wire 5 h RdOut [4:0] $end
    $var wire 1 j MemReadOut $end
    $var wire 1 k MemtoRegOut $end
    $var wire 1 l MemWriteOut $end
    $var wire 1 n RegWriteOut $end
    $var wire 64 "! ALUInput2 [63:0] $end
    $var wire 64 } alu_result [63:0] $end
    $var wire 1 !! zero_flag $end
   $upscope $end
   $scope module id_stage $end
    $var wire 1 &! clk $end
    $var wire 1 '! reset $end
    $var wire 32 c Instr [31:0] $end
    $var wire 1 n ExtRegWrite $end
    $var wire 1 n RegWrite $end
    $var wire 5 h WriteReg [4:0] $end
    $var wire 64 +! WriteData [63:0] $end
    $var wire 64 y ReadData1 [63:0] $end
    $var wire 64 { ReadData2 [63:0] $end
    $var wire 64 f ImmExt [63:0] $end
    $var wire 5 h Rd [4:0] $end
    $var wire 1 i Branch $end
    $var wire 1 j MemRead $end
    $var wire 1 k MemtoReg $end
    $var wire 4 o ALUOp [3:0] $end
    $var wire 1 l MemWrite $end
    $var wire 1 m ALUSrc $end
    $var wire 1 r RegDst $end
    $var wire 7 s opcode [6:0] $end
    $var wire 5 t rd_addr [4:0] $end
    $var wire 3 u funct3 [2:0] $end
    $var wire 5 v rs1_addr [4:0] $end
    $var wire 5 w rs2_addr [4:0] $end
    $var wire 7 x funct7 [6:0] $end
    $var wire 64 # registers[0] [63:0] $end
    $var wire 64 % registers[1] [63:0] $end
    $var wire 64 ' registers[2] [63:0] $end
    $var wire 64 ) registers[3] [63:0] $end
    $var wire 64 + registers[4] [63:0] $end
    $var wire 64 - registers[5] [63:0] $end
    $var wire 64 / registers[6] [63:0] $end
    $var wire 64 1 registers[7] [63:0] $end
    $var wire 64 3 registers[8] [63:0] $end
    $var wire 64 5 registers[9] [63:0] $end
    $var wire 64 7 registers[10] [63:0] $end
    $var wire 64 9 registers[11] [63:0] $end
    $var wire 64 ; registers[12] [63:0] $end
    $var wire 64 = registers[13] [63:0] $end
    $var wire 64 ? registers[14] [63:0] $end
    $var wire 64 A registers[15] [63:0] $end
    $var wire 64 C registers[16] [63:0] $end
    $var wire 64 E registers[17] [63:0] $end
    $var wire 64 G registers[18] [63:0] $end
    $var wire 64 I registers[19] [63:0] $end
    $var wire 64 K registers[20] [63:0] $end
    $var wire 64 M registers[21] [63:0] $end
    $var wire 64 O registers[22] [63:0] $end
    $var wire 64 Q registers[23] [63:0] $end
    $var wire 64 S registers[24] [63:0] $end
    $var wire 64 U registers[25] [63:0] $end
    $var wire 64 W registers[26] [63:0] $end
    $var wire 64 Y registers[27] [63:0] $end
    $var wire 64 [ registers[28] [63:0] $end
    $var wire 64 ] registers[29] [63:0] $end
    $var wire 64 _ registers[30] [63:0] $end
    $var wire 64 a registers[31] [63:0] $end
    $var wire 64 f imm [63:0] $end
    $var wire 1 i branch $end
    $var wire 1 j memRead $end
    $var wire 1 k memtoReg $end
    $var wire 1 l memWrite $end
    $var wire 1 m aluSrc $end
    $var wire 1 r regDst $end
    $var wire 1 n regWriteInt $end
    $var wire 4 o aluOp [3:0] $end
   $upscope $end
   $scope module if_stage $end
    $var wire 1 &! clk $end
    $var wire 1 -! rst_n $end
    $var wire 1 0! stall $end
    $var wire 1 (! branch_taken $end
    $var wire 64 p branch_target_addr [63:0] $end
    $var wire 32 c instruction [31:0] $end
    $var wire 64 d pc_current [63:0] $end
    $var wire 64 .! pc_next [63:0] $end
   $upscope $end
   $scope module mem_stage $end
    $var wire 1 &! clk $end
    $var wire 1 '! reset $end
    $var wire 64 } ALUResult [63:0] $end
    $var wire 64 { WriteData [63:0] $end
    $var wire 5 h Rd [4:0] $end
    $var wire 1 !! Zero $end
    $var wire 1 (! BranchTaken $end
    $var wire 1 j MemRead $end
    $var wire 1 l MemWrite $end
    $var wire 1 k MemtoReg $end
    $var wire 1 n RegWrite $end
    $var wire 64 )! ReadData [63:0] $end
    $var wire 64 } ALUResultOut [63:0] $end
    $var wire 5 h RdOut [4:0] $end
    $var wire 1 (! BranchTakenOut $end
    $var wire 1 k MemtoRegOut $end
    $var wire 1 n RegWriteOut $end
    $var wire 64 )! read_data [63:0] $end
    $var wire 10 $! mem_addr [9:0] $end
    $var wire 1 %! addr_valid $end
   $upscope $end
   $scope module wb_stage $end
    $var wire 64 )! ReadData [63:0] $end
    $var wire 64 } ALUResult [63:0] $end
    $var wire 5 h Rd [4:0] $end
    $var wire 1 k MemtoReg $end
    $var wire 1 n RegWrite $end
    $var wire 64 +! WriteData [63:0] $end
    $var wire 5 h WriteReg [4:0] $end
    $var wire 1 n RegWriteOut $end
   $upscope $end
  $upscope $end
 $upscope $end
$enddefinitions $end


#0
b0000000000000000000000000000000000000000000000000000000000000000 #
b0000000000000000000000000000000000000000000000000000000000000000 %
b0000000000000000000000000000000000000000000000000000000000000000 '
b0000000000000000000000000000000000000000000000000000000000000000 )
b0000000000000000000000000000000000000000000000000000000000000000 +
b0000000000000000000000000000000000000000000000000000000000000000 -
b0000000000000000000000000000000000000000000000000000000000000000 /
b0000000000000000000000000000000000000000000000000000000000000000 1
b0000000000000000000000000000000000000000000000000000000000000000 3
b0000000000000000000000000000000000000000000000000000000000000000 5
b0000000000000000000000000000000000000000000000000000000000000000 7
b0000000000000000000000000000000000000000000000000000000000000000 9
b0000000000000000000000000000000000000000000000000000000000000000 ;
b0000000000000000000000000000000000000000000000000000000000000000 =
b0000000000000000000000000000000000000000000000000000000000000000 ?
b0000000000000000000000000000000000000000000000000000000000000000 A
b0000000000000000000000000000000000000000000000000000000000000000 C
b0000000000000000000000000000000000000000000000000000000000000000 E
b0000000000000000000000000000000000000000000000000000000000000000 G
b0000000000000000000000000000000000000000000000000000000000000000 I
b0000000000000000000000000000000000000000000000000000000000000000 K
b0000000000000000000000000000000000000000000000000000000000000000 M
b0000000000000000000000000000000000000000000000000000000000000000 O
b0000000000000000000000000000000000000000000000000000000000000000 Q
b0000000000000000000000000000000000000000000000000000000000000000 S
b0000000000000000000000000000000000000000000000000000000000000000 U
b0000000000000000000000000000000000000000000000000000000000000000 W
b0000000000000000000000000000000000000000000000000000000000000000 Y
b0000000000000000000000000000000000000000000000000000000000000000 [
b0000000000000000000000000000000000000000000000000000000000000000 ]
b0000000000000000000000000000000000000000000000000000000000000000 _
b0000000000000000000000000000000000000000000000000000000000000000 a
b00000000000000000000000000000000 c
b0000000000000000000000000000000000000000000000000000000000000000 d
b0000000000000000000000000000000000000000000000000000000000000000 f
b00000 h
0i
0j
0k
0l
0m
0n
b0000 o
b1111111111111111111111111111111111111111111111111111111111111100 p
0r
b0000000 s
b00000 t
b000 u
b00000 v
b00000 w
b0000000 x
b0000000000000000000000000000000000000000000000000000000000000000 y
b0000000000000000000000000000000000000000000000000000000000000000 {
b0000000000000000000000000000000000000000000000000000000000000000 }
1!!
b0000000000000000000000000000000000000000000000000000000000000000 "!
b0000000000 $!
1%!
1&!
0'!
0(!
b0000000000000000000000000000000000000000000000000000000000000000 )!
b0000000000000000000000000000000000000000000000000000000000000000 +!
1-!
b0000000000000000000000000000000000000000000000000000000000000100 .!
00!
#1
0&!
#2
b0000000000000000000000000000000000000000000000000000000000000100 d
b0000000000000000000000000000000000000000000000000000000000000000 p
1&!
b0000000000000000000000000000000000000000000000000000000000001000 .!
#3
0&!
#4
b0000000000000000000000000000000000000000000000000000000000001000 d
b0000000000000000000000000000000000000000000000000000000000000100 p
1&!
b0000000000000000000000000000000000000000000000000000000000001100 .!
#5
0&!
#6
b0000000000000000000000000000000000000000000000000000000000001100 d
b0000000000000000000000000000000000000000000000000000000000001000 p
1&!
b0000000000000000000000000000000000000000000000000000000000010000 .!
#7
0&!
#8
b0000000000000000000000000000000000000000000000000000000000010000 d
b0000000000000000000000000000000000000000000000000000000000001100 p
1&!
b0000000000000000000000000000000000000000000000000000000000010100 .!
#9
0&!
#10
b0000000000000000000000000000000000000000000000000000000000010100 d
b0000000000000000000000000000000000000000000000000000000000010000 p
1&!
b0000000000000000000000000000000000000000000000000000000000011000 .!
#11
0&!
#12
b0000000000000000000000000000000000000000000000000000000000011000 d
b0000000000000000000000000000000000000000000000000000000000010100 p
1&!
b0000000000000000000000000000000000000000000000000000000000011100 .!
#13
0&!
#14
b0000000000000000000000000000000000000000000000000000000000011100 d
b0000000000000000000000000000000000000000000000000000000000011000 p
1&!
b0000000000000000000000000000000000000000000000000000000000100000 .!
#15
0&!
#16
b0000000000000000000000000000000000000000000000000000000000100000 d
b0000000000000000000000000000000000000000000000000000000000011100 p
1&!
b0000000000000000000000000000000000000000000000000000000000100100 .!
#17
0&!
#18
b0000000000000000000000000000000000000000000000000000000000100100 d
b0000000000000000000000000000000000000000000000000000000000100000 p
1&!
b0000000000000000000000000000000000000000000000000000000000101000 .!
#19
0&!
#20
b0000000000000000000000000000000000000000000000000000000000101000 d
b0000000000000000000000000000000000000000000000000000000000100100 p
1&!
b0000000000000000000000000000000000000000000000000000000000101100 .!
#21
0&!
#22
b0000000000000000000000000000000000000000000000000000000000101100 d
b0000000000000000000000000000000000000000000000000000000000101000 p
1&!
b0000000000000000000000000000000000000000000000000000000000110000 .!
#23
0&!
#24
b0000000000000000000000000000000000000000000000000000000000110000 d
b0000000000000000000000000000000000000000000000000000000000101100 p
1&!
b0000000000000000000000000000000000000000000000000000000000110100 .!
#25
0&!
#26
b0000000000000000000000000000000000000000000000000000000000110100 d
b0000000000000000000000000000000000000000000000000000000000110000 p
1&!
b0000000000000000000000000000000000000000000000000000000000111000 .!
#27
0&!
#28
b0000000000000000000000000000000000000000000000000000000000111000 d
b0000000000000000000000000000000000000000000000000000000000110100 p
1&!
b0000000000000000000000000000000000000000000000000000000000111100 .!
#29
0&!
#30
b0000000000000000000000000000000000000000000000000000000000111100 d
b0000000000000000000000000000000000000000000000000000000000111000 p
1&!
b0000000000000000000000000000000000000000000000000000000001000000 .!
#31
0&!
#32
b0000000000000000000000000000000000000000000000000000000001000000 d
b0000000000000000000000000000000000000000000000000000000000111100 p
1&!
b0000000000000000000000000000000000000000000000000000000001000100 .!
#33
0&!
#34
b0000000000000000000000000000000000000000000000000000000001000100 d
b0000000000000000000000000000000000000000000000000000000001000000 p
1&!
b0000000000000000000000000000000000000000000000000000000001001000 .!
#35
0&!
#36
b0000000000000000000000000000000000000000000000000000000001001000 d
b0000000000000000000000000000000000000000000000000000000001000100 p
1&!
b0000000000000000000000000000000000000000000000000000000001001100 .!
#37
0&!
#38
b0000000000000000000000000000000000000000000000000000000001001100 d
b0000000000000000000000000000000000000000000000000000000001001000 p
1&!
b0000000000000000000000000000000000000000000000000000000001010000 .!
#39
0&!
#40
b0000000000000000000000000000000000000000000000000000000001010000 d
b0000000000000000000000000000000000000000000000000000000001001100 p
1&!
b0000000000000000000000000000000000000000000000000000000001010100 .!
#41
0&!
#42
b0000000000000000000000000000000000000000000000000000000001010100 d
b0000000000000000000000000000000000000000000000000000000001010000 p
1&!
b0000000000000000000000000000000000000000000000000000000001011000 .!
#43
0&!
#44
b0000000000000000000000000000000000000000000000000000000001011000 d
b0000000000000000000000000000000000000000000000000000000001010100 p
1&!
b0000000000000000000000000000000000000000000000000000000001011100 .!
#45
0&!
#46
b0000000000000000000000000000000000000000000000000000000001011100 d
b0000000000000000000000000000000000000000000000000000000001011000 p
1&!
b0000000000000000000000000000000000000000000000000000000001100000 .!
#47
0&!
#48
b0000000000000000000000000000000000000000000000000000000001100000 d
b0000000000000000000000000000000000000000000000000000000001011100 p
1&!
b0000000000000000000000000000000000000000000000000000000001100100 .!
#49
0&!
#50
b0000000000000000000000000000000000000000000000000000000001100100 d
b0000000000000000000000000000000000000000000000000000000001100000 p
1&!
b0000000000000000000000000000000000000000000000000000000001101000 .!
#51
0&!
#52
b0000000000000000000000000000000000000000000000000000000001101000 d
b0000000000000000000000000000000000000000000000000000000001100100 p
1&!
b0000000000000000000000000000000000000000000000000000000001101100 .!
#53
0&!
#54
b0000000000000000000000000000000000000000000000000000000001101100 d
b0000000000000000000000000000000000000000000000000000000001101000 p
1&!
b0000000000000000000000000000000000000000000000000000000001110000 .!
#55
0&!
#56
b0000000000000000000000000000000000000000000000000000000001110000 d
b0000000000000000000000000000000000000000000000000000000001101100 p
1&!
b0000000000000000000000000000000000000000000000000000000001110100 .!
#57
0&!
#58
b0000000000000000000000000000000000000000000000000000000001110100 d
b0000000000000000000000000000000000000000000000000000000001110000 p
1&!
b0000000000000000000000000000000000000000000000000000000001111000 .!
#59
0&!
#60
b0000000000000000000000000000000000000000000000000000000001111000 d
b0000000000000000000000000000000000000000000000000000000001110100 p
1&!
b0000000000000000000000000000000000000000000000000000000001111100 .!
#61
0&!
#62
b0000000000000000000000000000000000000000000000000000000001111100 d
b0000000000000000000000000000000000000000000000000000000001111000 p
1&!
b0000000000000000000000000000000000000000000000000000000010000000 .!
#63
0&!
#64
b0000000000000000000000000000000000000000000000000000000010000000 d
b0000000000000000000000000000000000000000000000000000000001111100 p
1&!
b0000000000000000000000000000000000000000000000000000000010000100 .!
#65
0&!
#66
b0000000000000000000000000000000000000000000000000000000010000100 d
b0000000000000000000000000000000000000000000000000000000010000000 p
1&!
b0000000000000000000000000000000000000000000000000000000010001000 .!
#67
0&!
#68
b0000000000000000000000000000000000000000000000000000000010001000 d
b0000000000000000000000000000000000000000000000000000000010000100 p
1&!
b0000000000000000000000000000000000000000000000000000000010001100 .!
#69
0&!
#70
b0000000000000000000000000000000000000000000000000000000010001100 d
b0000000000000000000000000000000000000000000000000000000010001000 p
1&!
b0000000000000000000000000000000000000000000000000000000010010000 .!
#71
0&!
#72
b0000000000000000000000000000000000000000000000000000000010010000 d
b0000000000000000000000000000000000000000000000000000000010001100 p
1&!
b0000000000000000000000000000000000000000000000000000000010010100 .!
#73
0&!
#74
b0000000000000000000000000000000000000000000000000000000010010100 d
b0000000000000000000000000000000000000000000000000000000010010000 p
1&!
b0000000000000000000000000000000000000000000000000000000010011000 .!
#75
0&!
#76
b0000000000000000000000000000000000000000000000000000000010011000 d
b0000000000000000000000000000000000000000000000000000000010010100 p
1&!
b0000000000000000000000000000000000000000000000000000000010011100 .!
#77
0&!
#78
b0000000000000000000000000000000000000000000000000000000010011100 d
b0000000000000000000000000000000000000000000000000000000010011000 p
1&!
b0000000000000000000000000000000000000000000000000000000010100000 .!
#79
0&!
#80
b0000000000000000000000000000000000000000000000000000000010100000 d
b0000000000000000000000000000000000000000000000000000000010011100 p
1&!
b0000000000000000000000000000000000000000000000000000000010100100 .!
#81
0&!
#82
b0000000000000000000000000000000000000000000000000000000010100100 d
b0000000000000000000000000000000000000000000000000000000010100000 p
1&!
b0000000000000000000000000000000000000000000000000000000010101000 .!
#83
0&!
#84
b0000000000000000000000000000000000000000000000000000000010101000 d
b0000000000000000000000000000000000000000000000000000000010100100 p
1&!
b0000000000000000000000000000000000000000000000000000000010101100 .!
#85
0&!
#86
b0000000000000000000000000000000000000000000000000000000010101100 d
b0000000000000000000000000000000000000000000000000000000010101000 p
1&!
b0000000000000000000000000000000000000000000000000000000010110000 .!
#87
0&!
#88
b0000000000000000000000000000000000000000000000000000000010110000 d
b0000000000000000000000000000000000000000000000000000000010101100 p
1&!
b0000000000000000000000000000000000000000000000000000000010110100 .!
#89
0&!
#90
b0000000000000000000000000000000000000000000000000000000010110100 d
b0000000000000000000000000000000000000000000000000000000010110000 p
1&!
b0000000000000000000000000000000000000000000000000000000010111000 .!
#91
0&!
#92
b0000000000000000000000000000000000000000000000000000000010111000 d
b0000000000000000000000000000000000000000000000000000000010110100 p
1&!
b0000000000000000000000000000000000000000000000000000000010111100 .!
#93
0&!
#94
b0000000000000000000000000000000000000000000000000000000010111100 d
b0000000000000000000000000000000000000000000000000000000010111000 p
1&!
b0000000000000000000000000000000000000000000000000000000011000000 .!
#95
0&!
#96
b0000000000000000000000000000000000000000000000000000000011000000 d
b0000000000000000000000000000000000000000000000000000000010111100 p
1&!
b0000000000000000000000000000000000000000000000000000000011000100 .!
#97
0&!
#98
b0000000000000000000000000000000000000000000000000000000011000100 d
b0000000000000000000000000000000000000000000000000000000011000000 p
1&!
b0000000000000000000000000000000000000000000000000000000011001000 .!
