fetch.v
module instruction_fetch (
    input wire clk,              // System clock
    input wire rst_n,            // Active low reset
    input wire stall,            // Stall signal from hazard unit
    input wire branch_taken,     // Branch taken signal
    input wire [63:0] branch_target_addr, // Branch target address
    output reg [31:0] instruction,  // 32-bit instruction fetched
    output reg [63:0] pc_current,   // Current program counter
    output reg [63:0] pc_next       // Next program counter (pc+4)
);

    // Instruction memory (could be replaced with actual memory interface)
    reg [31:0] instr_mem [0:1023];  // 1024 entries of 32-bit instructions
    
    // Initialize PC
    initial begin
        pc_current = 64'h0000_0000_0000_0000;  // Starting address
        pc_next = 64'h0000_0000_0000_0004;     // Initialize pc_next as well
        instruction = 32'h0000_0000;           // Initialize instruction to NOP
    end
    
    // Instruction fetch logic
    always @(posedge clk or negedge rst_n) begin
        if (!rst_n) begin
            // Reset state
            pc_current <= 64'h0000_0000_0000_0000;
            pc_next <= 64'h0000_0000_0000_0004;
            instruction <= 32'h0000_0000;  // NOP instruction
        end 
        else if (!stall) begin
            // Update PC
            if (branch_taken) begin
                pc_current <= branch_target_addr;  // Jump to branch target
                pc_next <= branch_target_addr + 64'h4;
            end 
            else begin
                pc_current <= pc_next;  // Normal sequential execution
                pc_next <= pc_next + 64'h4;
            end
            
            // Fetch instruction from memory based on PC
            // The memory is accessed using the PC value directly
            // For proper alignment, we need to select the correct word
            instruction <= instr_mem[(pc_current >> 2)];
        end
        // If stalled, maintain the current state (PC and instruction remain unchanged)
    end
    
    // Memory initialization could be done here or via external file
    // initial $readmemh("program.hex", instr_mem);

endmodule

tb/fetch_tb.v
`timescale 1ns/1ps

module instruction_fetch_tb;
    reg clk, rst_n, stall, branch_taken;
    reg [63:0] branch_target_addr;
    wire [31:0] instruction;
    wire [63:0] pc_current;
    
    instruction_fetch dut (
        .clk(clk),
        .rst_n(rst_n),
        .stall(stall),
        .branch_taken(branch_taken),
        .branch_target_addr(branch_target_addr),
        .instruction(instruction),
        .pc_current(pc_current)
    );
    
    // Clock: 100MHz (10ns period)
    initial clk = 0;
    always #5 clk = ~clk;
    
    initial begin
        dut.instr_mem[0] = 32'h00000013;  // NOP
        dut.instr_mem[1] = 32'h00500113;  // addi x2, x0, 5
        dut.instr_mem[2] = 32'h00310233;  // add x4, x2, x3
        dut.instr_mem[3] = 32'hFE000AE3;  // beq x0, x0, -12
        dut.instr_mem[4] = 32'h00628293;  // addi x5, x5, 6
        dut.instr_mem[10] = 32'h00700393; // addi x7, x0, 7
        dut.instr_mem[11] = 32'h00700393;
    end
    
    initial begin
        rst_n = 0;
        stall = 0;
        branch_taken = 0;
        branch_target_addr = 64'h0;
        
        #15 rst_n = 1;
        
        #30;
        
        // Test stall
        stall = 1;
        #20;
        stall = 0;
        #10;
        
        // Test branch
        branch_taken = 1;
        branch_target_addr = 64'h28; // Jump to address 0x28
        #10;
        branch_taken = 0;
        #20;
        
        // Test reset
        rst_n = 0;
        #10;
        rst_n = 1;
        #30;
        
        $display("Fetch testbench completed");
        $finish;
    end
    
    initial begin
        $monitor("T=%0t | RST=%b | STALL=%b | BR=%b | PC=%h | INSTR=%h",
                 $time, rst_n, stall, branch_taken, pc_current, instruction);
    end
    
    initial begin
        $dumpfile("instruction_fetch_tb.vcd");
        $dumpvars(0, instruction_fetch_tb);
    end

endmodule

tb/instruction_fetch_tb.vcd
$date
	Fri Jan 30 11:11:39 2026
$end
$version
	Icarus Verilog
$end
$timescale
	1ps
$end
$scope module instruction_fetch_tb $end
$var wire 64 ! pc_current [63:0] $end
$var wire 32 " instruction [31:0] $end
$var reg 1 # branch_taken $end
$var reg 64 $ branch_target_addr [63:0] $end
$var reg 1 % clk $end
$var reg 1 & rst_n $end
$var reg 1 ' stall $end
$scope module dut $end
$var wire 1 # branch_taken $end
$var wire 64 ( branch_target_addr [63:0] $end
$var wire 1 % clk $end
$var wire 1 & rst_n $end
$var wire 1 ' stall $end
$var wire 64 ) pc_next [63:0] $end
$var reg 32 * instruction [31:0] $end
$var reg 64 + pc_current [63:0] $end
$upscope $end
$upscope $end
$enddefinitions $end
$comment Show the parameter values. $end
$dumpall
$end
#0
$dumpvars
b0 +
b10011 *
b100 )
b0 (
0'
0&
0%
b0 $
0#
b10011 "
b0 !
$end
#5000
1%
#10000
0%
#15000
b1000 )
b10100000000000100010011 "
b10100000000000100010011 *
b100 !
b100 +
1%
1&
#20000
0%
#25000
b1100 )
b1100010000001000110011 "
b1100010000001000110011 *
b1000 !
b1000 +
1%
#30000
0%
#35000
b10000 )
b11111110000000000000101011100011 "
b11111110000000000000101011100011 *
b1100 !
b1100 +
1%
#40000
0%
#45000
1%
1'
#50000
0%
#55000
1%
#60000
0%
#65000
b10100 )
b11000101000001010010011 "
b11000101000001010010011 *
b10000 !
b10000 +
1%
0'
#70000
0%
#75000
b11100000000001110010011 "
b11100000000001110010011 *
b101000 !
b101000 +
b101000 )
1%
b101000 $
b101000 (
1#
#80000
0%
#85000
b101100 !
b101100 +
b110000 )
1%
0#
#90000
0%
#95000
b110100 )
bx "
bx *
b110000 !
b110000 +
1%
#100000
0%
#105000
b100 )
b10011 "
b10011 *
b0 !
b0 +
1%
0&
#110000
0%
#115000
b1000 )
b10100000000000100010011 "
b10100000000000100010011 *
b100 !
b100 +
1%
1&
#120000
0%
#125000
b1100 )
b1100010000001000110011 "
b1100010000001000110011 *
b1000 !
b1000 +
1%
#130000
0%
#135000
b10000 )
b11111110000000000000101011100011 "
b11111110000000000000101011100011 *
b1100 !
b1100 +
1%
#140000
0%
#145000
b10100 )
b11000101000001010010011 "
b11000101000001010010011 *
b10000 !
b10000 +
1%
