writeback.v
module writeback (
    // Input signals from memory stage
    input wire [63:0] ReadData,       // Data read from memory
    input wire [63:0] ALUResult,      // Result from ALU
    input wire [4:0] Rd,              // Destination register
    
    // Control signals from memory stage
    input wire MemtoReg,              // Memory to register control
    input wire RegWrite,              // Register write control
    
    // Output signals to register file
    output wire [63:0] WriteData,     // Data to write to register file
    output wire [4:0] WriteReg,       // Register to write to
    output wire RegWriteOut           // Register write control
);
    // Select data to write back to register file
    assign WriteData = MemtoReg ? ReadData : ALUResult;
    
    // Pass through destination register
    assign WriteReg = Rd;
    
    // Pass through register write control
    assign RegWriteOut = RegWrite;
    
endmodule

rtl/memory.v
module memory (
    input wire clk,
    input wire reset,
    input wire [63:0] ALUResult,
    input wire [63:0] WriteData,
    input wire [4:0] Rd,
    input wire Zero,
    input wire BranchTaken,
    input wire MemRead,
    input wire MemWrite,
    input wire MemtoReg,
    input wire RegWrite,
    output wire [63:0] ReadData,
    output wire [63:0] ALUResultOut,
    output wire [4:0] RdOut,
    output wire BranchTakenOut,
    output wire MemtoRegOut,
    output wire RegWriteOut
);

// Data memory: 1024 x 64-bit = 8KB
reg [63:0] mem [0:1023]/*verilator public*/;
reg [63:0] read_data;

// Memory address calculation (byte to word)
wire [9:0] mem_addr = ALUResult[12:3];

// Check if address is valid (< 8192 bytes = 1024 words * 8 bytes)
wire addr_valid = (ALUResult < 64'd8192);  

// Memory read (combinational)
always @(*) begin
    if (MemRead && addr_valid)
        read_data = mem[mem_addr];
    else
        read_data = 64'd0;
end

// Memory write (synchronous)
always @(posedge clk) begin
    if (!reset && MemWrite && addr_valid) begin
        mem[mem_addr] <= WriteData;
    end
end

assign ReadData = read_data;
assign ALUResultOut = ALUResult;
assign RdOut = Rd;
assign BranchTakenOut = BranchTaken;
assign MemtoRegOut = MemtoReg;
assign RegWriteOut = RegWrite;

endmodule

rtl/execute.v
module execute (
    input wire [63:0] ReadData1,
    input wire [63:0] ReadData2,
    input wire [63:0] ImmExt,
    input wire [4:0] Rd,
    input wire [3:0] ALUOp,
    input wire ALUSrc,
    input wire Branch,
    input wire MemRead,
    input wire MemtoReg,
    input wire MemWrite,
    input wire RegWrite,
    
    output wire [63:0] ALUResult,
    output wire Zero,
    output wire BranchTaken,
    output wire [63:0] WriteData,
    output wire [4:0] RdOut,
    output wire MemReadOut,
    output wire MemtoRegOut,
    output wire MemWriteOut,
    output wire RegWriteOut
);

    // ALU input selection
    wire [63:0] ALUInput2 = ALUSrc ? ImmExt : ReadData2;
    
    // ALU computation
    reg [63:0] alu_result;
    reg zero_flag;
    
    always @(*) begin
        case (ALUOp)
            4'b0010: alu_result = ReadData1 + ALUInput2;  // ADD
            4'b0110: alu_result = ReadData1 - ALUInput2;  // SUB
            4'b0111: alu_result = ReadData1 & ALUInput2;  // AND
            4'b0001: alu_result = ReadData1 | ALUInput2;  // OR
            4'b0000: alu_result = ReadData1 + ALUInput2;  // ADD (for ld/sd)
            default: alu_result = 64'd0;
        endcase
        
        zero_flag = (alu_result == 64'd0);
    end
    
    // Branch decision
    assign BranchTaken = Branch & zero_flag;
    
    // Outputs
    assign ALUResult = alu_result;
    assign Zero = zero_flag;
    assign WriteData = ReadData2;
    assign RdOut = Rd;
    
    // Control forwarding
    assign MemReadOut = MemRead;
    assign MemtoRegOut = MemtoReg;
    assign MemWriteOut = MemWrite;
    assign RegWriteOut = RegWrite;

endmodule

rtl/decode.v
module decode (
    input wire clk,
    input wire reset,
    input wire [31:0] Instr,
    input wire ExtRegWrite,
    output wire RegWrite,
    input wire [4:0] WriteReg,
    input wire [63:0] WriteData,
    output wire [63:0] ReadData1,
    output wire [63:0] ReadData2,
    output wire [63:0] ImmExt,
    output wire [4:0] Rd,
    output wire Branch,
    output wire MemRead,
    output wire MemtoReg,
    output wire [3:0] ALUOp,
    output wire MemWrite,
    output wire ALUSrc,
    output wire RegDst
);

    wire [6:0] opcode = Instr[6:0];
    wire [4:0] rd_addr = Instr[11:7];
    wire [2:0] funct3 = Instr[14:12];
    wire [4:0] rs1_addr = Instr[19:15];
    wire [4:0] rs2_addr = Instr[24:20];
    wire [6:0] funct7 = Instr[31:25];
    
    // Register file
    reg [63:0] registers [0:31]/*verilator public*/;
    
    // Register read (combinational with x0 hardwired to 0)
    assign ReadData1 = (rs1_addr == 5'd0) ? 64'd0 : registers[rs1_addr];
    assign ReadData2 = (rs2_addr == 5'd0) ? 64'd0 : registers[rs2_addr];
    
    // Register write (synchronous)
    always @(posedge clk) begin
        if (ExtRegWrite && (WriteReg != 5'd0))
            registers[WriteReg] <= WriteData;
    end
    
    // Immediate generation (combinational)
    reg [63:0] imm;
    always @(*) begin
        case (opcode)
            7'b0000011: // I-type (ld)
                imm = {{52{Instr[31]}}, Instr[31:20]};
            7'b0100011: // S-type (sd)
                imm = {{52{Instr[31]}}, Instr[31:25], Instr[11:7]};
            7'b1100011: // B-type (beq)
                imm = {{51{Instr[31]}}, Instr[31], Instr[7], Instr[30:25], Instr[11:8], 1'b0};
            default:
                imm = 64'd0;
        endcase
    end
    assign ImmExt = imm;
    
    // Control signal generation
    reg branch, memRead, memtoReg, memWrite, aluSrc, regDst, regWriteInt;
    reg [3:0] aluOp;
    
    always @(*) begin
        // Defaults
        {branch, memRead, memtoReg, memWrite, aluSrc, regDst, regWriteInt} = 7'b0;
        aluOp = 4'b0000;
        
        case (opcode)
            7'b0110011: begin // R-type
                regDst = 1'b1;
                regWriteInt = 1'b1;
                case ({funct3, funct7[5]})
                    4'b0000: aluOp = 4'b0010; // add
                    4'b0001: aluOp = 4'b0110; // sub
                    4'b1110: aluOp = 4'b0111; // and
                    4'b1100: aluOp = 4'b0001; // or
                    default: aluOp = 4'b0000;
                endcase
            end
            
            7'b0000011: begin // ld (I-type load)
                regDst = 1'b1;
                aluSrc = 1'b1;
                memtoReg = 1'b1;
                regWriteInt = 1'b1;
                memRead = 1'b1;
            end
            
            7'b0100011: begin // sd (S-type store)
                aluSrc = 1'b1;
                memWrite = 1'b1;
            end
            
            7'b1100011: begin // beq (B-type branch)
                branch = 1'b1;
                aluOp = 4'b0110;
            end
        endcase
    end
    
    assign Branch = branch;
    assign MemRead = memRead;
    assign MemtoReg = memtoReg;
    assign ALUOp = aluOp;
    assign MemWrite = memWrite;
    assign ALUSrc = aluSrc;
    assign RegDst = regDst;
    assign RegWrite = regWriteInt;
    
    // Rd output (0 for S-type and B-type)
    assign Rd = (opcode == 7'b0100011 || opcode == 7'b1100011) ? 5'd0 : rd_addr;

endmodule

rtl/instruction_fetch.v
module instruction_fetch (
    input wire clk,
    input wire rst_n,
    input wire stall,
    input wire branch_taken,
    input wire [63:0] branch_target_addr,
    output reg [31:0] instruction,
    output reg [63:0] pc_current
);

    // Instruction memory - 1024 x 32-bit
    reg [31:0] instr_mem [0:1023] /*verilator public*/;


    initial begin
        integer i;
        // 1. Clear memory
        for (i=0; i<1024; i=i+1) instr_mem[i] = 32'b0;

        // addi x6, x0, 5   (x6 = 5)
        instr_mem[0] = 32'h00500313;
        
        // addi x7, x0, 10  (x7 = 10)
        instr_mem[1] = 32'h00a00393;
        
        // add x8, x6, x7   (x8 = 5 + 10 = 15)
        instr_mem[2] = 32'h00730433;
        
        // nop (addi x0, x0, 0)
        instr_mem[3] = 32'h00000013;
    end

    wire [63:0] pc_next;
    assign pc_next = branch_taken ? branch_target_addr : (pc_current + 64'd4);

    always @(posedge clk or negedge rst_n) begin
        if (!rst_n) begin
            pc_current <= 64'h0;
            instruction <= 32'h00000013; // NOP
        end 
        else if (!stall) begin
            pc_current <= pc_next;
            instruction <= instr_mem[pc_current[11:2]]; 
        end
        // If stalled, maintain current state
    end

endmodule

rtl/single_cycle_processor.v
// Single-Cycle RISC-V Processor Implementation
`timescale 1ns/1ps

module single_cycle_processor (
    input wire clk,
    input wire reset
);

    // Fetch stage outputs
    wire [31:0] instruction /*verilator public*/;
    wire [63:0] pc_current /*verilator public*/;
    
    // Decode stage outputs
    wire [63:0] read_data1, read_data2, imm_ext;
    wire [4:0] rd;
    wire branch, mem_read, mem_to_reg, mem_write, alu_src, reg_write;
    wire [3:0] alu_op;
    
    // Execute stage outputs
    wire [63:0] alu_result, write_data_mem;
    wire zero, branch_taken;
    wire [4:0] rd_ex;
    wire mem_read_ex, mem_to_reg_ex, mem_write_ex, reg_write_ex;
    
    // Memory stage outputs
    wire [63:0] read_data_mem, alu_result_mem;
    wire [4:0] rd_mem;
    wire mem_to_reg_mem, reg_write_mem;
    
    // Writeback stage outputs
    wire [63:0] write_data_reg;
    wire [4:0] write_reg;
    wire reg_write_wb;
    
    // Branch target calculation
    wire [63:0] branch_target_addr = (pc_current - 64'd4) + imm_ext;    
    // Instruction Fetch
    instruction_fetch if_stage (
        .clk(clk),
        .rst_n(~reset),
        .stall(1'b0),
        .branch_taken(branch_taken),
        .branch_target_addr(branch_target_addr),
        .instruction(instruction),
        .pc_current(pc_current)
    );
    
    // Decode
    decode id_stage (
        .clk(clk),
        .reset(reset),
        .Instr(instruction),
        .ExtRegWrite(reg_write_wb),
        .RegWrite(reg_write),
        .WriteReg(write_reg),
        .WriteData(write_data_reg),
        .ReadData1(read_data1),
        .ReadData2(read_data2),
        .ImmExt(imm_ext),
        .Rd(rd),
        .Branch(branch),
        .MemRead(mem_read),
        .MemtoReg(mem_to_reg),
        .ALUOp(alu_op),
        .MemWrite(mem_write),
        .ALUSrc(alu_src),
        .RegDst()  // Unused in single-cycle
    );
    
    // Execute
    execute ex_stage (
        .ReadData1(read_data1),
        .ReadData2(read_data2),
        .ImmExt(imm_ext),
        .Rd(rd),
        .ALUOp(alu_op),
        .ALUSrc(alu_src),
        .Branch(branch),
        .MemRead(mem_read),
        .MemtoReg(mem_to_reg),
        .MemWrite(mem_write),
        .RegWrite(reg_write),
        .ALUResult(alu_result),
        .Zero(zero),
        .BranchTaken(branch_taken),
        .WriteData(write_data_mem),
        .RdOut(rd_ex),
        .MemReadOut(mem_read_ex),
        .MemtoRegOut(mem_to_reg_ex),
        .MemWriteOut(mem_write_ex),
        .RegWriteOut(reg_write_ex)
    );
    
    // Memory
    memory mem_stage (
        .clk(clk),
        .reset(reset),
        .ALUResult(alu_result),
        .WriteData(write_data_mem),
        .Rd(rd_ex),
        .Zero(zero),
        .BranchTaken(branch_taken),
        .MemRead(mem_read_ex),
        .MemWrite(mem_write_ex),
        .MemtoReg(mem_to_reg_ex),
        .RegWrite(reg_write_ex),
        .ReadData(read_data_mem),
        .ALUResultOut(alu_result_mem),
        .RdOut(rd_mem),
        .BranchTakenOut(),  // Unused
        .MemtoRegOut(mem_to_reg_mem),
        .RegWriteOut(reg_write_mem)
    );
    
    // Writeback
    writeback wb_stage (
        .ReadData(read_data_mem),
        .ALUResult(alu_result_mem),
        .Rd(rd_mem),
        .MemtoReg(mem_to_reg_mem),
        .RegWrite(reg_write_mem),
        .WriteData(write_data_reg),
        .WriteReg(write_reg),
        .RegWriteOut(reg_write_wb)
    );

endmodule

tb/waveform.vcd
$version Generated by VerilatedVcd $end
$timescale 1ps $end
 $scope module TOP $end
  $scope module single_cycle_processor $end
   $var wire 1 7 clk $end
   $var wire 1 8 reset $end
   $var wire 32 9 instruction [31:0] $end
   $var wire 64 : pc_current [63:0] $end
   $var wire 64 < read_data1 [63:0] $end
   $var wire 64 . read_data2 [63:0] $end
   $var wire 64 $ imm_ext [63:0] $end
   $var wire 5 > rd [4:0] $end
   $var wire 1 & branch $end
   $var wire 1 ' mem_read $end
   $var wire 1 ( mem_to_reg $end
   $var wire 1 ) mem_write $end
   $var wire 1 * alu_src $end
   $var wire 1 + reg_write $end
   $var wire 4 , alu_op [3:0] $end
   $var wire 64 0 alu_result [63:0] $end
   $var wire 64 . write_data_mem [63:0] $end
   $var wire 1 2 zero $end
   $var wire 1 ? branch_taken $end
   $var wire 5 > rd_ex [4:0] $end
   $var wire 1 ' mem_read_ex $end
   $var wire 1 ( mem_to_reg_ex $end
   $var wire 1 ) mem_write_ex $end
   $var wire 1 + reg_write_ex $end
   $var wire 64 @ read_data_mem [63:0] $end
   $var wire 64 0 alu_result_mem [63:0] $end
   $var wire 5 > rd_mem [4:0] $end
   $var wire 1 ( mem_to_reg_mem $end
   $var wire 1 + reg_write_mem $end
   $var wire 64 B write_data_reg [63:0] $end
   $var wire 5 > write_reg [4:0] $end
   $var wire 1 + reg_write_wb $end
   $var wire 64 D branch_target_addr [63:0] $end
   $scope module if_stage $end
    $var wire 1 7 clk $end
    $var wire 1 F rst_n $end
    $var wire 1 4! stall $end
    $var wire 1 ? branch_taken $end
    $var wire 64 D branch_target_addr [63:0] $end
    $var wire 32 G instruction [31:0] $end
    $var wire 64 H pc_current [63:0] $end
    $var wire 64 J pc_next [63:0] $end
    $scope module unnamedblk1 $end
     $var wire 32 # i [31:0] $end
    $upscope $end
   $upscope $end
   $scope module id_stage $end
    $var wire 1 7 clk $end
    $var wire 1 8 reset $end
    $var wire 32 9 Instr [31:0] $end
    $var wire 1 + ExtRegWrite $end
    $var wire 1 + RegWrite $end
    $var wire 5 > WriteReg [4:0] $end
    $var wire 64 B WriteData [63:0] $end
    $var wire 64 < ReadData1 [63:0] $end
    $var wire 64 . ReadData2 [63:0] $end
    $var wire 64 $ ImmExt [63:0] $end
    $var wire 5 > Rd [4:0] $end
    $var wire 1 & Branch $end
    $var wire 1 ' MemRead $end
    $var wire 1 ( MemtoReg $end
    $var wire 4 , ALUOp [3:0] $end
    $var wire 1 ) MemWrite $end
    $var wire 1 * ALUSrc $end
    $var wire 1 - RegDst $end
    $var wire 7 L opcode [6:0] $end
    $var wire 5 M rd_addr [4:0] $end
    $var wire 3 N funct3 [2:0] $end
    $var wire 5 O rs1_addr [4:0] $end
    $var wire 5 P rs2_addr [4:0] $end
    $var wire 7 Q funct7 [6:0] $end
    $var wire 64 R registers[0] [63:0] $end
    $var wire 64 T registers[1] [63:0] $end
    $var wire 64 V registers[2] [63:0] $end
    $var wire 64 X registers[3] [63:0] $end
    $var wire 64 Z registers[4] [63:0] $end
    $var wire 64 \ registers[5] [63:0] $end
    $var wire 64 ^ registers[6] [63:0] $end
    $var wire 64 ` registers[7] [63:0] $end
    $var wire 64 b registers[8] [63:0] $end
    $var wire 64 d registers[9] [63:0] $end
    $var wire 64 f registers[10] [63:0] $end
    $var wire 64 h registers[11] [63:0] $end
    $var wire 64 j registers[12] [63:0] $end
    $var wire 64 l registers[13] [63:0] $end
    $var wire 64 n registers[14] [63:0] $end
    $var wire 64 p registers[15] [63:0] $end
    $var wire 64 r registers[16] [63:0] $end
    $var wire 64 t registers[17] [63:0] $end
    $var wire 64 v registers[18] [63:0] $end
    $var wire 64 x registers[19] [63:0] $end
    $var wire 64 z registers[20] [63:0] $end
    $var wire 64 | registers[21] [63:0] $end
    $var wire 64 ~ registers[22] [63:0] $end
    $var wire 64 "! registers[23] [63:0] $end
    $var wire 64 $! registers[24] [63:0] $end
    $var wire 64 &! registers[25] [63:0] $end
    $var wire 64 (! registers[26] [63:0] $end
    $var wire 64 *! registers[27] [63:0] $end
    $var wire 64 ,! registers[28] [63:0] $end
    $var wire 64 .! registers[29] [63:0] $end
    $var wire 64 0! registers[30] [63:0] $end
    $var wire 64 2! registers[31] [63:0] $end
    $var wire 64 $ imm [63:0] $end
    $var wire 1 & branch $end
    $var wire 1 ' memRead $end
    $var wire 1 ( memtoReg $end
    $var wire 1 ) memWrite $end
    $var wire 1 * aluSrc $end
    $var wire 1 - regDst $end
    $var wire 1 + regWriteInt $end
    $var wire 4 , aluOp [3:0] $end
   $upscope $end
   $scope module mem_stage $end
    $var wire 1 7 clk $end
    $var wire 1 8 reset $end
    $var wire 64 0 ALUResult [63:0] $end
    $var wire 64 . WriteData [63:0] $end
    $var wire 5 > Rd [4:0] $end
    $var wire 1 2 Zero $end
    $var wire 1 ? BranchTaken $end
    $var wire 1 ' MemRead $end
    $var wire 1 ) MemWrite $end
    $var wire 1 ( MemtoReg $end
    $var wire 1 + RegWrite $end
    $var wire 64 @ ReadData [63:0] $end
    $var wire 64 0 ALUResultOut [63:0] $end
    $var wire 5 > RdOut [4:0] $end
    $var wire 1 ? BranchTakenOut $end
    $var wire 1 ( MemtoRegOut $end
    $var wire 1 + RegWriteOut $end
    $var wire 64 @ read_data [63:0] $end
    $var wire 10 5 mem_addr [9:0] $end
    $var wire 1 6 addr_valid $end
   $upscope $end
   $scope module ex_stage $end
    $var wire 64 < ReadData1 [63:0] $end
    $var wire 64 . ReadData2 [63:0] $end
    $var wire 64 $ ImmExt [63:0] $end
    $var wire 5 > Rd [4:0] $end
    $var wire 4 , ALUOp [3:0] $end
    $var wire 1 * ALUSrc $end
    $var wire 1 & Branch $end
    $var wire 1 ' MemRead $end
    $var wire 1 ( MemtoReg $end
    $var wire 1 ) MemWrite $end
    $var wire 1 + RegWrite $end
    $var wire 64 0 ALUResult [63:0] $end
    $var wire 1 2 Zero $end
    $var wire 1 ? BranchTaken $end
    $var wire 64 . WriteData [63:0] $end
    $var wire 5 > RdOut [4:0] $end
    $var wire 1 ' MemReadOut $end
    $var wire 1 ( MemtoRegOut $end
    $var wire 1 ) MemWriteOut $end
    $var wire 1 + RegWriteOut $end
    $var wire 64 3 ALUInput2 [63:0] $end
    $var wire 64 0 alu_result [63:0] $end
    $var wire 1 2 zero_flag $end
   $upscope $end
   $scope module wb_stage $end
    $var wire 64 @ ReadData [63:0] $end
    $var wire 64 0 ALUResult [63:0] $end
    $var wire 5 > Rd [4:0] $end
    $var wire 1 ( MemtoReg $end
    $var wire 1 + RegWrite $end
    $var wire 64 B WriteData [63:0] $end
    $var wire 5 > WriteReg [4:0] $end
    $var wire 1 + RegWriteOut $end
   $upscope $end
  $upscope $end
  $var wire 1 7 clk $end
  $var wire 1 8 reset $end
 $upscope $end
$enddefinitions $end


#0
b00000000000000000000010000000000 #
b0000000000000000000000000000000000000000000000000000000000000000 $
0&
0'
0(
0)
0*
0+
b0000 ,
0-
b0000000000000000000000000000000000000000000000000000000000000000 .
b0000000000000000000000000000000000000000000000000000000000000000 0
12
b0000000000000000000000000000000000000000000000000000000000000000 3
b0000000000 5
16
17
18
b00000000000000000000000000000000 9
b0000000000000000000000000000000000000000000000000000000000000000 :
b0000000000000000000000000000000000000000000000000000000000000000 <
b00000 >
0?
b0000000000000000000000000000000000000000000000000000000000000000 @
b0000000000000000000000000000000000000000000000000000000000000000 B
b1111111111111111111111111111111111111111111111111111111111111100 D
0F
b00000000000000000000000000000000 G
b0000000000000000000000000000000000000000000000000000000000000000 H
b0000000000000000000000000000000000000000000000000000000000000100 J
b0000000 L
b00000 M
b000 N
b00000 O
b00000 P
b0000000 Q
b0000000000000000000000000000000000000000000000000000000000000000 R
b0000000000000000000000000000000000000000000000000000000000000000 T
b0000000000000000000000000000000000000000000000000000000000000000 V
b0000000000000000000000000000000000000000000000000000000000000000 X
b0000000000000000000000000000000000000000000000000000000000000000 Z
b0000000000000000000000000000000000000000000000000000000000000000 \
b0000000000000000000000000000000000000000000000000000000000000000 ^
b0000000000000000000000000000000000000000000000000000000000000000 `
b0000000000000000000000000000000000000000000000000000000000000000 b
b0000000000000000000000000000000000000000000000000000000000000000 d
b0000000000000000000000000000000000000000000000000000000000000000 f
b0000000000000000000000000000000000000000000000000000000000000000 h
b0000000000000000000000000000000000000000000000000000000000000000 j
b0000000000000000000000000000000000000000000000000000000000000000 l
b0000000000000000000000000000000000000000000000000000000000000000 n
b0000000000000000000000000000000000000000000000000000000000000000 p
b0000000000000000000000000000000000000000000000000000000000000000 r
b0000000000000000000000000000000000000000000000000000000000000000 t
b0000000000000000000000000000000000000000000000000000000000000000 v
b0000000000000000000000000000000000000000000000000000000000000000 x
b0000000000000000000000000000000000000000000000000000000000000000 z
b0000000000000000000000000000000000000000000000000000000000000000 |
b0000000000000000000000000000000000000000000000000000000000000000 ~
b0000000000000000000000000000000000000000000000000000000000000000 "!
b0000000000000000000000000000000000000000000000000000000000000000 $!
b0000000000000000000000000000000000000000000000000000000000000000 &!
b0000000000000000000000000000000000000000000000000000000000000000 (!
b0000000000000000000000000000000000000000000000000000000000000000 *!
b0000000000000000000000000000000000000000000000000000000000000000 ,!
b0000000000000000000000000000000000000000000000000000000000000000 .!
b0000000000000000000000000000000000000000000000000000000000000000 0!
b0000000000000000000000000000000000000000000000000000000000000000 2!
04!
#1
07
#2
17
b00000000000000000000000000010011 9
b00000000000000000000000000010011 G
b0010011 L
#3
07
#4
17
#5
07
#6
17
#7
07
#8
17
#9
07
#10
17
08
b00000000010100000000001100010011 9
b0000000000000000000000000000000000000000000000000000000000000100 :
b00110 >
b0000000000000000000000000000000000000000000000000000000000000000 D
1F
b00000000010100000000001100010011 G
b0000000000000000000000000000000000000000000000000000000000000100 H
b0000000000000000000000000000000000000000000000000000000000001000 J
b00110 M
b00101 P
#11
07
#12
17
b00000000101000000000001110010011 9
b0000000000000000000000000000000000000000000000000000000000001000 :
b00111 >
b0000000000000000000000000000000000000000000000000000000000000100 D
b00000000101000000000001110010011 G
b0000000000000000000000000000000000000000000000000000000000001000 H
b0000000000000000000000000000000000000000000000000000000000001100 J
b00111 M
b01010 P
#13
07
#14
1+
b0010 ,
1-
17
b00000000011100110000010000110011 9
b0000000000000000000000000000000000000000000000000000000000001100 :
b01000 >
b0000000000000000000000000000000000000000000000000000000000001000 D
b00000000011100110000010000110011 G
b0000000000000000000000000000000000000000000000000000000000001100 H
b0000000000000000000000000000000000000000000000000000000000010000 J
b0110011 L
b01000 M
b00110 O
b00111 P
#15
07
#16
0+
b0000 ,
0-
17
b00000000000000000000000000010011 9
b0000000000000000000000000000000000000000000000000000000000010000 :
b00000 >
b0000000000000000000000000000000000000000000000000000000000001100 D
b00000000000000000000000000010011 G
b0000000000000000000000000000000000000000000000000000000000010000 H
b0000000000000000000000000000000000000000000000000000000000010100 J
b0010011 L
b00000 M
b00000 O
b00000 P
#17
07
#18
17
b00000000000000000000000000000000 9
b0000000000000000000000000000000000000000000000000000000000010100 :
b0000000000000000000000000000000000000000000000000000000000010000 D
b00000000000000000000000000000000 G
b0000000000000000000000000000000000000000000000000000000000010100 H
b0000000000000000000000000000000000000000000000000000000000011000 J
b0000000 L
#19
07
#20
17
b0000000000000000000000000000000000000000000000000000000000011000 :
b0000000000000000000000000000000000000000000000000000000000010100 D
b0000000000000000000000000000000000000000000000000000000000011000 H
b0000000000000000000000000000000000000000000000000000000000011100 J
#21
07
#22
17
b0000000000000000000000000000000000000000000000000000000000011100 :
b0000000000000000000000000000000000000000000000000000000000011000 D
b0000000000000000000000000000000000000000000000000000000000011100 H
b0000000000000000000000000000000000000000000000000000000000100000 J
#23
07
#24
17
b0000000000000000000000000000000000000000000000000000000000100000 :
b0000000000000000000000000000000000000000000000000000000000011100 D
b0000000000000000000000000000000000000000000000000000000000100000 H
b0000000000000000000000000000000000000000000000000000000000100100 J
#25
07
#26
17
b0000000000000000000000000000000000000000000000000000000000100100 :
b0000000000000000000000000000000000000000000000000000000000100000 D
b0000000000000000000000000000000000000000000000000000000000100100 H
b0000000000000000000000000000000000000000000000000000000000101000 J
#27
07
#28
17
b0000000000000000000000000000000000000000000000000000000000101000 :
b0000000000000000000000000000000000000000000000000000000000100100 D
b0000000000000000000000000000000000000000000000000000000000101000 H
b0000000000000000000000000000000000000000000000000000000000101100 J
#29
07
#30
17
b0000000000000000000000000000000000000000000000000000000000101100 :
b0000000000000000000000000000000000000000000000000000000000101000 D
b0000000000000000000000000000000000000000000000000000000000101100 H
b0000000000000000000000000000000000000000000000000000000000110000 J
#31
07
#32
17
b0000000000000000000000000000000000000000000000000000000000110000 :
b0000000000000000000000000000000000000000000000000000000000101100 D
b0000000000000000000000000000000000000000000000000000000000110000 H
b0000000000000000000000000000000000000000000000000000000000110100 J
#33
07
#34
17
b0000000000000000000000000000000000000000000000000000000000110100 :
b0000000000000000000000000000000000000000000000000000000000110000 D
b0000000000000000000000000000000000000000000000000000000000110100 H
b0000000000000000000000000000000000000000000000000000000000111000 J
#35
07
#36
17
b0000000000000000000000000000000000000000000000000000000000111000 :
b0000000000000000000000000000000000000000000000000000000000110100 D
b0000000000000000000000000000000000000000000000000000000000111000 H
b0000000000000000000000000000000000000000000000000000000000111100 J
#37
07
#38
17
b0000000000000000000000000000000000000000000000000000000000111100 :
b0000000000000000000000000000000000000000000000000000000000111000 D
b0000000000000000000000000000000000000000000000000000000000111100 H
b0000000000000000000000000000000000000000000000000000000001000000 J
#39
07
#40
17
b0000000000000000000000000000000000000000000000000000000001000000 :
b0000000000000000000000000000000000000000000000000000000000111100 D
b0000000000000000000000000000000000000000000000000000000001000000 H
b0000000000000000000000000000000000000000000000000000000001000100 J
#41
07
#42
17
b0000000000000000000000000000000000000000000000000000000001000100 :
b0000000000000000000000000000000000000000000000000000000001000000 D
b0000000000000000000000000000000000000000000000000000000001000100 H
b0000000000000000000000000000000000000000000000000000000001001000 J
#43
07
#44
17
b0000000000000000000000000000000000000000000000000000000001001000 :
b0000000000000000000000000000000000000000000000000000000001000100 D
b0000000000000000000000000000000000000000000000000000000001001000 H
b0000000000000000000000000000000000000000000000000000000001001100 J
#45
07
#46
17
b0000000000000000000000000000000000000000000000000000000001001100 :
b0000000000000000000000000000000000000000000000000000000001001000 D
b0000000000000000000000000000000000000000000000000000000001001100 H
b0000000000000000000000000000000000000000000000000000000001010000 J
#47
07
#48
17
b0000000000000000000000000000000000000000000000000000000001010000 :
b0000000000000000000000000000000000000000000000000000000001001100 D
b0000000000000000000000000000000000000000000000000000000001010000 H
b0000000000000000000000000000000000000000000000000000000001010100 J
#49
07
#50
17
b0000000000000000000000000000000000000000000000000000000001010100 :
b0000000000000000000000000000000000000000000000000000000001010000 D
b0000000000000000000000000000000000000000000000000000000001010100 H
b0000000000000000000000000000000000000000000000000000000001011000 J
#51
07
#52
17
b0000000000000000000000000000000000000000000000000000000001011000 :
b0000000000000000000000000000000000000000000000000000000001010100 D
b0000000000000000000000000000000000000000000000000000000001011000 H
b0000000000000000000000000000000000000000000000000000000001011100 J
#53
07
#54
17
b0000000000000000000000000000000000000000000000000000000001011100 :
b0000000000000000000000000000000000000000000000000000000001011000 D
b0000000000000000000000000000000000000000000000000000000001011100 H
b0000000000000000000000000000000000000000000000000000000001100000 J
#55
07
#56
17
b0000000000000000000000000000000000000000000000000000000001100000 :
b0000000000000000000000000000000000000000000000000000000001011100 D
b0000000000000000000000000000000000000000000000000000000001100000 H
b0000000000000000000000000000000000000000000000000000000001100100 J
#57
07
#58
17
b0000000000000000000000000000000000000000000000000000000001100100 :
b0000000000000000000000000000000000000000000000000000000001100000 D
b0000000000000000000000000000000000000000000000000000000001100100 H
b0000000000000000000000000000000000000000000000000000000001101000 J
#59
07
#60
17
b0000000000000000000000000000000000000000000000000000000001101000 :
b0000000000000000000000000000000000000000000000000000000001100100 D
b0000000000000000000000000000000000000000000000000000000001101000 H
b0000000000000000000000000000000000000000000000000000000001101100 J
#61
07
#62
17
b0000000000000000000000000000000000000000000000000000000001101100 :
b0000000000000000000000000000000000000000000000000000000001101000 D
b0000000000000000000000000000000000000000000000000000000001101100 H
b0000000000000000000000000000000000000000000000000000000001110000 J
#63
07
#64
17
b0000000000000000000000000000000000000000000000000000000001110000 :
b0000000000000000000000000000000000000000000000000000000001101100 D
b0000000000000000000000000000000000000000000000000000000001110000 H
b0000000000000000000000000000000000000000000000000000000001110100 J
#65
07
#66
17
b0000000000000000000000000000000000000000000000000000000001110100 :
b0000000000000000000000000000000000000000000000000000000001110000 D
b0000000000000000000000000000000000000000000000000000000001110100 H
b0000000000000000000000000000000000000000000000000000000001111000 J
#67
07
#68
17
b0000000000000000000000000000000000000000000000000000000001111000 :
b0000000000000000000000000000000000000000000000000000000001110100 D
b0000000000000000000000000000000000000000000000000000000001111000 H
b0000000000000000000000000000000000000000000000000000000001111100 J
#69
07
#70
17
b0000000000000000000000000000000000000000000000000000000001111100 :
b0000000000000000000000000000000000000000000000000000000001111000 D
b0000000000000000000000000000000000000000000000000000000001111100 H
b0000000000000000000000000000000000000000000000000000000010000000 J
#71
07
#72
17
b0000000000000000000000000000000000000000000000000000000010000000 :
b0000000000000000000000000000000000000000000000000000000001111100 D
b0000000000000000000000000000000000000000000000000000000010000000 H
b0000000000000000000000000000000000000000000000000000000010000100 J
#73
07
#74
17
b0000000000000000000000000000000000000000000000000000000010000100 :
b0000000000000000000000000000000000000000000000000000000010000000 D
b0000000000000000000000000000000000000000000000000000000010000100 H
b0000000000000000000000000000000000000000000000000000000010001000 J
#75
07
#76
17
b0000000000000000000000000000000000000000000000000000000010001000 :
b0000000000000000000000000000000000000000000000000000000010000100 D
b0000000000000000000000000000000000000000000000000000000010001000 H
b0000000000000000000000000000000000000000000000000000000010001100 J
#77
07
#78
17
b0000000000000000000000000000000000000000000000000000000010001100 :
b0000000000000000000000000000000000000000000000000000000010001000 D
b0000000000000000000000000000000000000000000000000000000010001100 H
b0000000000000000000000000000000000000000000000000000000010010000 J
#79
07
#80
17
b0000000000000000000000000000000000000000000000000000000010010000 :
b0000000000000000000000000000000000000000000000000000000010001100 D
b0000000000000000000000000000000000000000000000000000000010010000 H
b0000000000000000000000000000000000000000000000000000000010010100 J
#81
07
#82
17
b0000000000000000000000000000000000000000000000000000000010010100 :
b0000000000000000000000000000000000000000000000000000000010010000 D
b0000000000000000000000000000000000000000000000000000000010010100 H
b0000000000000000000000000000000000000000000000000000000010011000 J
#83
07
#84
17
b0000000000000000000000000000000000000000000000000000000010011000 :
b0000000000000000000000000000000000000000000000000000000010010100 D
b0000000000000000000000000000000000000000000000000000000010011000 H
b0000000000000000000000000000000000000000000000000000000010011100 J
#85
07
